tests/__init__.py
tests/mock.py
tests/test_scheduler.py
vistudio/__init__.py
vistudio/annotation/__init__.py
vistudio/annotation/api/__init__.py
vistudio/annotation/api/annotation.py
vistudio/annotation/client/__init__.py
vistudio/annotation/client/annotation_api_annotationset.py
vistudio/annotation/client/annotation_client.py
vistudio/annotation/config/__init__.py
vistudio/annotation/config/arg_parser.py
vistudio/annotation/config/config.py
vistudio/annotation/datasink/__init__.py
vistudio/annotation/datasink/csv_datasink.py
vistudio/annotation/datasink/filename_provider.py
vistudio/annotation/datasource/__init__.py
vistudio/annotation/datasource/image_datasource.py
vistudio/annotation/datasource/mongo_query_pipeline.py
vistudio/annotation/datasource/sharded_mongo_datasource.py
vistudio/annotation/datasource/xml_datasource.py
vistudio/annotation/operator/__init__.py
vistudio/annotation/operator/archiver.py
vistudio/annotation/operator/cityscapes_formatter.py
vistudio/annotation/operator/coco_formatter.py
vistudio/annotation/operator/cvat_formatter.py
vistudio/annotation/operator/filter.py
vistudio/annotation/operator/image_formatter.py
vistudio/annotation/operator/imagenet_formatter.py
vistudio/annotation/operator/label_formatter.py
vistudio/annotation/operator/paddleclas_formatter.py
vistudio/annotation/operator/paddleseg_formatter.py
vistudio/annotation/operator/reader.py
vistudio/annotation/operator/thumbnail_generator.py
vistudio/annotation/operator/vistudio_cutter.py
vistudio/annotation/operator/vistudio_formatter.py
vistudio/annotation/operator/webp_generator.py
vistudio/annotation/operator/webp_state_updater.py
vistudio/annotation/operator/zip_formatter.py
vistudio/annotation/operator/updater/__init__.py
vistudio/annotation/operator/updater/annotation_state_updater.py
vistudio/annotation/operator/updater/base_mongo_updater.py
vistudio/annotation/operator/updater/image_created_at_updater.py
vistudio/annotation/operator/updater/thumbnail_state_updater.py
vistudio_annotation-1.3.4.4.dist-info/METADATA
vistudio_annotation-1.3.4.4.dist-info/WHEEL
vistudio_annotation-1.3.4.4.dist-info/top_level.txt
vistudio_annotation-1.3.4.4.dist-info/RECORD
