Metadata-Version: 2.1
Name: vistudio-annotation
Version: 1.3.4.4
Summary: sdk in python for annotation
Home-page: https://console.cloud.baidu-int.com/devops/icode/repos/baidu/bce-vistudio/vistudio-annotation/tree/master/sdk
Author: yangtingyu01
Author-email: yangtingyu01@baidu.com
License: MIT
Classifier: Programming Language :: Python
Classifier: Programming Language :: Python :: 3
Classifier: Programming Language :: Python :: 3.7
Classifier: Programming Language :: Python :: 3.8
Classifier: Programming Language :: Python :: 3.9
Requires-Python: >=3.6
Requires-Dist: APScheduler (==3.10.4)
Requires-Dist: bce-internal-sdk (==1.0.0.1)
Requires-Dist: bce-python-sdk (==0.8.87)
Requires-Dist: bcelogger (==1.2.0.4)
Requires-Dist: gaea-logit (==1.2.0)
Requires-Dist: gaea-operator (==1.2.0.2)
Requires-Dist: mongoengine (==0.28.2)
Requires-Dist: multidict (==6.0.4)
Requires-Dist: opencv-python-headless (==4.8.1.78)
Requires-Dist: pandas (==2.0.3)
Requires-Dist: pyarrow (==15.0.1)
Requires-Dist: pycocotools (==2.0.7)
Requires-Dist: pymongo (==4.6.1)
Requires-Dist: pymongoarrow (==1.3.0)
Requires-Dist: PyYAML (==6.0.1)
Requires-Dist: ray (==2.11.0)
Requires-Dist: s3fs (==2024.3.1)
Requires-Dist: setuptools (==68.2.2)
Requires-Dist: windmill-artifact (==1.0.0.10)
Requires-Dist: windmill-compute (==1.0.0.18)
Requires-Dist: windmill-train (==1.0.0.13)
Requires-Dist: xxhash (==3.4.1)
